adk_sim_testing/__init__.py
adk_sim_testing/helpers.py
adk_sim_testing/proto_helpers.py
adk_sim_testing/simulated_human.py
adk_sim_testing/fixtures/__init__.py
adk_sim_testing/fixtures/fake_event_repo.py
adk_sim_testing/fixtures/fake_session_repo.py
adk_sim_testing-0.1.22.dist-info/METADATA
adk_sim_testing-0.1.22.dist-info/WHEEL
adk_sim_testing-0.1.22.dist-info/RECORD
