Metadata-Version: 2.4
Name: adk-sim-testing
Version: 0.1.22
Summary: Testing utilities for ADK Simulator
Requires-Python: >=3.14
Requires-Dist: adk-sim-protos==0.1.22
Requires-Dist: google-adk>=1.21.0
Requires-Dist: pytest>=9.0.1
Requires-Dist: sqlalchemy>=2.0.0
